etc/.gitconfig/.gitconfig
git_global/__init__.py
git_global/cli.py
git_global/metadata.py
git_global-0.0.4.data/data/bin/git-global
git_global-0.0.4.dist-info/LICENSE
git_global-0.0.4.dist-info/METADATA
git_global-0.0.4.dist-info/WHEEL
git_global-0.0.4.dist-info/entry_points.txt
git_global-0.0.4.dist-info/top_level.txt
git_global-0.0.4.dist-info/RECORD
