Metadata-Version: 2.1
Name: git-global
Version: 0.0.4
Summary: UNKNOWN
License: UNKNOWN
Platform: UNKNOWN
Requires-Python: >=3.9
License-File: LICENSE
Provides-Extra: test
Requires-Dist: pytest ; extra == 'test'
